portmod/__init__.py
portmod/_version.py
portmod/cache.py
portmod/cfg_protect.py
portmod/download.py
portmod/execute.py
portmod/functools.py
portmod/globals.py
portmod/io.py
portmod/loader.py
portmod/lock.py
portmod/merge.py
portmod/modules.py
portmod/news.py
portmod/package.py
portmod/perms.py
portmod/prefix.py
portmod/prompt.py
portmod/py.typed
portmod/pybuild.py
portmod/query.py
portmod/repos.py
portmod/source.py
portmod/sync.py
portmod/transactions.py
portmod/tsort.py
portmod/typing.py
portmod/util.py
portmod/vdb.py
portmod/win32.py
portmod/_cli/__init__.py
portmod/_cli/cfg_update.py
portmod/_cli/destroy.py
portmod/_cli/error.py
portmod/_cli/init.py
portmod/_cli/inquisitor.py
portmod/_cli/main.py
portmod/_cli/merge.py
portmod/_cli/mirror.py
portmod/_cli/outdated.py
portmod/_cli/pybuild.py
portmod/_cli/query.py
portmod/_cli/run.py
portmod/_cli/search.py
portmod/_cli/select.py
portmod/_cli/sync.py
portmod/_cli/use.py
portmod/_cli/validate.py
portmod/_deprecated/__init__.py
portmod/_deprecated/rebuild.py
portmod/_deprecated/vfs.py
portmod/_deps/__init__.py
portmod/_deps/formula.py
portmod/_deps/tokens.py
portmod/_deps/weights.py
portmod/_gui/.pylintrc
portmod/_gui/__init__.py
portmod/_gui/config.py
portmod/_gui/human_bytes.py
portmod/_gui/l10n.py
portmod/_gui/main.qml
portmod/_gui/packages.py
portmod/_gui/Manage/DetailsLabel.qml
portmod/_gui/Manage/FlagListModel.py
portmod/_gui/Manage/InstalledPackagesModel.py
portmod/_gui/Manage/InstalledPackagesPanel.qml
portmod/_gui/Manage/ManageTab.qml
portmod/_gui/Manage/PackageDetailsPanel.qml
portmod/_gui/Manage/__init__.py
portmod/_gui/Search/SearchPackagesModel.py
portmod/_gui/Search/SearchTab.qml
portmod/_gui/Search/__init__.py
portmod/config/__init__.py
portmod/config/license.py
portmod/config/mask.py
portmod/config/profiles.py
portmod/config/pyconf.py
portmod/config/sets.py
portmod/config/textures.py
portmod/config/use.py
portmod/fs/__init__.py
portmod/parsers/__init__.py
portmod/parsers/flags.py
portmod-2.9.1.dist-info/licenses/AUTHORS
portmod-2.9.1.dist-info/licenses/LICENSE
portmod-2.9.1.dist-info/METADATA
portmod-2.9.1.dist-info/WHEEL
portmod-2.9.1.dist-info/entry_points.txt
portmod-2.9.1.dist-info/top_level.txt
portmod-2.9.1.dist-info/RECORD
