Metadata-Version: 2.4
Name: portmod
Version: 2.9.1
Summary: A CLI package manager for mods
Home-page: https://gitlab.com/portmod/portmod
Download-URL: https://gitlab.com/portmod/portmod/-/releases
Author: Portmod Authors
Author-email: incoming+portmod-portmod-9660349-issue-@incoming.gitlab.com
License: GPLv3
Classifier: Development Status :: 5 - Production/Stable
Classifier: Environment :: Console
Classifier: Intended Audience :: End Users/Desktop
Classifier: License :: OSI Approved :: GNU General Public License v3 (GPLv3)
Classifier: Operating System :: MacOS
Classifier: Operating System :: Microsoft :: Windows
Classifier: Operating System :: POSIX :: Linux
Classifier: Programming Language :: Python
Classifier: Programming Language :: Python :: 3.8
Classifier: Programming Language :: Python :: 3.9
Classifier: Programming Language :: Python :: 3.10
Classifier: Programming Language :: Python :: 3.11
Classifier: Programming Language :: Python :: 3 :: Only
Classifier: Topic :: Games/Entertainment
Classifier: Topic :: System :: Software Distribution
Requires-Python: >=3.8
License-File: LICENSE
License-File: AUTHORS
Requires-Dist: colorama
Requires-Dist: GitPython
Requires-Dist: progressbar2>=3.7
Requires-Dist: pywin32; platform_system == "Windows"
Requires-Dist: RestrictedPython>=4.0
Requires-Dist: redbaron
Requires-Dist: python-sat!=0.1.7.dev22,!=0.1.7.dev23,!=0.1.7.dev24,>=0.1.5.dev0
Requires-Dist: python-sat>=0.1.5.dev12; platform_system == "Windows"
Requires-Dist: requests
Requires-Dist: packaging
Requires-Dist: fasteners>=0.16
Requires-Dist: chardet
Requires-Dist: patool
Provides-Extra: dev
Requires-Dist: black; extra == "dev"
Requires-Dist: flake8; extra == "dev"
Requires-Dist: pylint; extra == "dev"
Requires-Dist: isort; extra == "dev"
Requires-Dist: mypy; extra == "dev"
Requires-Dist: deprecated; extra == "dev"
Provides-Extra: test
Requires-Dist: pytest; extra == "test"
Requires-Dist: pytest-cov; extra == "test"
Requires-Dist: setuptools_scm; extra == "test"
Provides-Extra: benchmark
Requires-Dist: pytest-benchmark; extra == "benchmark"
Provides-Extra: bash
Requires-Dist: argcomplete; extra == "bash"
Provides-Extra: man
Requires-Dist: sphinx; extra == "man"
Requires-Dist: sphinx-argparse; extra == "man"
Requires-Dist: autodocsumm; extra == "man"
Requires-Dist: sphinx-autodoc-typehints; extra == "man"
Requires-Dist: sphinxcontrib-apidoc; extra == "man"
Requires-Dist: deprecated; extra == "man"
Provides-Extra: doc
Requires-Dist: sphinx; extra == "doc"
Requires-Dist: sphinx-argparse; extra == "doc"
Requires-Dist: autodocsumm; extra == "doc"
Requires-Dist: sphinx-autodoc-typehints; extra == "doc"
Requires-Dist: sphinxcontrib-apidoc; extra == "doc"
Requires-Dist: deprecated; extra == "doc"
Requires-Dist: sphinx_rtd_theme; extra == "doc"
Provides-Extra: gui
Requires-Dist: PySide6-Essentials; extra == "gui"
Dynamic: author
Dynamic: author-email
Dynamic: classifier
Dynamic: description
Dynamic: description-content-type
Dynamic: download-url
Dynamic: home-page
Dynamic: license
Dynamic: license-file
Dynamic: provides-extra
Dynamic: requires-dist
Dynamic: requires-python
Dynamic: summary
